{
  "id": "quiz-demo",
  "name": "English Grammar Quiz",
  "description": "Test your knowledge of English grammar",
  "learningMode": "quiz",
  "level": "intermediate",
  "category": "Grammar",
  "tags": ["grammar", "quiz", "test"],
  "estimatedTime": 10,
  "difficulty": 3,
  "data": [
    {
      "id": "q1",
      "question": "Which sentence is grammatically correct?",
      "options": [
        "She don't like coffee.",
        "She doesn't like coffee.",
        "She not like coffee.",
        "She no likes coffee."
      ],
      "correct": 1,
      "explanation": "The correct form uses 'doesn't' (does not) with third person singular subjects."
    },
    {
      "id": "q2",
      "question": "What is the past tense of 'go'?",
      "options": [
        "goed",
        "gone",
        "went",
        "going"
      ],
      "correct": 2,
      "explanation": "'Went' is the simple past tense of 'go'. 'Gone' is the past participle."
    },
    {
      "id": "q3",
      "question": "Choose the correct preposition: 'I'm interested ___ learning English.'",
      "options": [
        "on",
        "in",
        "at",
        "for"
      ],
      "correct": 1,
      "explanation": "We use 'interested in' when talking about hobbies or activities we want to do."
    },
    {
      "id": "q4",
      "question": "Which is the correct comparative form of 'good'?",
      "options": [
        "gooder",
        "more good",
        "better",
        "best"
      ],
      "correct": 2,
      "explanation": "'Better' is the comparative form of 'good'. 'Best' is the superlative form."
    },
    {
      "id": "q5",
      "question": "Complete the sentence: 'If I ___ rich, I would travel the world.'",
      "options": [
        "am",
        "was",
        "were",
        "will be"
      ],
      "correct": 2,
      "explanation": "In second conditional sentences, we use 'were' for all persons after 'if'."
    }
  ]
}